semantic_ai/__init__.py
semantic_ai/config.py
semantic_ai/constants.py
semantic_ai/exceptions.py
semantic_ai/extract.py
semantic_ai/main.py
semantic_ai/utils.py
semantic_ai/connectors/__init__.py
semantic_ai/connectors/base.py
semantic_ai/connectors/mysql.py
semantic_ai/connectors/sqlite.py
semantic_ai/connectors/microsoft/__init__.py
semantic_ai/connectors/microsoft/sharepoint.py
semantic_ai/embeddings/__init__.py
semantic_ai/embeddings/base.py
semantic_ai/embeddings/huggingface.py
semantic_ai/embeddings/openai.py
semantic_ai/examples/__init__.py
semantic_ai/examples/elasticsearch_ibm.py
semantic_ai/examples/sharepoint.py
semantic_ai/examples/test_mysql_search.py
semantic_ai/examples/test_sqlite_search.py
semantic_ai/indexer/__init__.py
semantic_ai/indexer/base.py
semantic_ai/indexer/elastic_search.py
semantic_ai/indexer/opensearch.py
semantic_ai/indexer/qdrant.py
semantic_ai/llm/__init__.py
semantic_ai/llm/base.py
semantic_ai/llm/ibm.py
semantic_ai/llm/llama.py
semantic_ai/llm/openai.py
semantic_ai/nlp/__init__.py
semantic_ai/nlp/prompt.py
semantic_ai/search/__init__.py
semantic_ai/search/semantic_search.py
semantic_ai-0.0.6.1.dist-info/LICENSE
semantic_ai-0.0.6.1.dist-info/METADATA
semantic_ai-0.0.6.1.dist-info/WHEEL
semantic_ai-0.0.6.1.dist-info/entry_points.txt
semantic_ai-0.0.6.1.dist-info/top_level.txt
semantic_ai-0.0.6.1.dist-info/RECORD
