Metadata-Version: 2.1
Name: semantic_ai
Version: 0.0.6.1
Summary: Sematic AI RAG System
Home-page: https://github.com/decisionfacts/semantic-ai
Download-URL: https://github.com/decisionfacts/semantic-ai.git
Author: DecisionFacts
Author-email: info@decisionfacts.io
Maintainer: DecisionFacts
Maintainer-email: info@decisionfacts.io
License: Apache License 2.0
Keywords: pdf machine-learning ocr deep-neural-networks openai docx approximate-nearest-neighbor-search semantic-search document-parser rag fastapi vector-database inference-api openai-api llm retrieval-augmented-generation llama2 
License-File: LICENSE
Requires-Dist: langchain ==0.0.336
Requires-Dist: sentence-transformers ==2.2.2
Requires-Dist: df-extract ==0.0.2.1
Requires-Dist: elasticsearch ==8.8.2
Requires-Dist: qdrant-client ==1.4.0
Requires-Dist: jq ==1.4.0
Requires-Dist: httpx ==0.25.0
Requires-Dist: pydantic ==1.10.11
Requires-Dist: fastapi ==0.95.1
Requires-Dist: auto-gptq ==0.5.0
Requires-Dist: openai ==1.2.0
Requires-Dist: uvicorn ==0.22.0
Requires-Dist: tiktoken ==0.4.0
Requires-Dist: ibm-watson-machine-learning ==1.0.327
Requires-Dist: langchain-experimental ==0.0.24
Requires-Dist: python-dotenv ==1.0.0
Requires-Dist: mysql-connector-python ==8.3.0
Requires-Dist: pyodbc ==5.0.1
Requires-Dist: SQLAlchemy ==2.0.23
Requires-Dist: opensearch-py ==2.6.0
